plte/__init__.py
plte/module.py
plte-0.1.dist-info/LICENSE
plte-0.1.dist-info/METADATA
plte-0.1.dist-info/WHEEL
plte-0.1.dist-info/top_level.txt
plte-0.1.dist-info/RECORD
