Metadata-Version: 2.1
Name: plte
Version: 0.1
Summary: A Python package for data processing
Author: Python Master
Author-email: srinivasskr707srinivasskr707@gmail.com
Classifier: Programming Language :: Python :: 3
Classifier: License :: OSI Approved :: MIT License
Classifier: Operating System :: OS Independent
Requires-Python: >=3.6
License-File: LICENSE
